pykkn/build_multi_parameters.py
pykkn/dataset.py
pykkn/dataset_image.py
pykkn/dataset_video.py
pykkn/instrument.py
pykkn/model.py
pykkn/parameter.py
pykkn/parse.py
pykkn/parse_json.py
pykkn/pipeline.py
pykkn/run.py
pykkn/storage.py
pykkn-1.5.8.dist-info/LICENSE
pykkn-1.5.8.dist-info/WHEEL
pykkn-1.5.8.dist-info/METADATA
pykkn-1.5.8.dist-info/RECORD
